postmark_incoming/__init__.py
postmark_incoming/admin.py
postmark_incoming/apps.py
postmark_incoming/factories.py
postmark_incoming/models.py
postmark_incoming/urls.py
postmark_incoming/views.py
postmark_incoming/migrations/__init__.py
postmark_incoming/tests/__init__.py
postmark_incoming/tests/conftest.py
postmark_incoming/tests/settings.py
postmark_incoming/tests/test_webhook.py
postmark_incoming/tests/urls.py
django_postmark_incoming-0.0.1.dist-info/LICENSE
django_postmark_incoming-0.0.1.dist-info/METADATA
django_postmark_incoming-0.0.1.dist-info/WHEEL
django_postmark_incoming-0.0.1.dist-info/top_level.txt
django_postmark_incoming-0.0.1.dist-info/RECORD
